cdk_athena/__init__.py
cdk_athena/py.typed
cdk_athena/_jsii/__init__.py
cdk_athena/_jsii/cdk-athena@3.0.0.jsii.tgz
cdk_athena-3.0.0.dist-info/LICENSE
cdk_athena-3.0.0.dist-info/METADATA
cdk_athena-3.0.0.dist-info/WHEEL
cdk_athena-3.0.0.dist-info/top_level.txt
cdk_athena-3.0.0.dist-info/RECORD
