Metadata-Version: 2.1
Name: cdk-athena
Version: 3.0.0
Summary: CDK Construct for creating Athena resources
Home-page: https://github.com/udondan/cdk-athena
Author: Daniel Schroeder
License: Apache-2.0
Project-URL: Source, https://github.com/udondan/cdk-athena.git
Platform: UNKNOWN
Classifier: Intended Audience :: Developers
Classifier: Operating System :: OS Independent
Classifier: Programming Language :: JavaScript
Classifier: Programming Language :: Python :: 3 :: Only
Classifier: Programming Language :: Python :: 3.7
Classifier: Programming Language :: Python :: 3.8
Classifier: Programming Language :: Python :: 3.9
Classifier: Programming Language :: Python :: 3.10
Classifier: Typing :: Typed
Classifier: Development Status :: 5 - Production/Stable
Classifier: License :: OSI Approved
Requires-Python: ~=3.7
License-File: LICENSE
Requires-Dist: aws-cdk-lib (<3.0.0,>=2.0.0)
Requires-Dist: constructs (<11.0.0,>=10.0.0)
Requires-Dist: jsii (<2.0.0,>=1.58.0)
Requires-Dist: publication (>=0.0.3)
